<annotation verified="yes">
	<folder>result</folder>
	<filename>1-5-007.jpg</filename>
	<path>D:\Project\YoutubeData\result\1-5-007.jpg</path>
	<source>
		<database>Unknown</database>
	</source>
	<size>
		<width>1280</width>
		<height>720</height>
		<depth>3</depth>
	</size>
	<segmented>0</segmented>
	<object>
		<name>runway</name>
		<pose>Unspecified</pose>
		<truncated>0</truncated>
		<difficult>0</difficult>
		<bndbox>
			<xmin>601</xmin>
			<ymin>316</ymin>
			<xmax>656</xmax>
			<ymax>361</ymax>
		</bndbox>
	</object>
	<object>
		<name>entrance</name>
		<pose>Unspecified</pose>
		<truncated>0</truncated>
		<difficult>0</difficult>
		<bndbox>
			<xmin>604</xmin>
			<ymin>350</ymin>
			<xmax>651</xmax>
			<ymax>358</ymax>
		</bndbox>
	</object>
</annotation>
