<annotation verified="yes">
	<folder>result</folder>
	<filename>1-82-008.jpg</filename>
	<path>D:\Project\YoutubeData\result\1-82-008.jpg</path>
	<source>
		<database>Unknown</database>
	</source>
	<size>
		<width>1920</width>
		<height>1080</height>
		<depth>3</depth>
	</size>
	<segmented>0</segmented>
	<object>
		<name>runway</name>
		<pose>Unspecified</pose>
		<truncated>0</truncated>
		<difficult>0</difficult>
		<bndbox>
			<xmin>884</xmin>
			<ymin>661</ymin>
			<xmax>936</xmax>
			<ymax>717</ymax>
		</bndbox>
	</object>
	<object>
		<name>entrance</name>
		<pose>Unspecified</pose>
		<truncated>0</truncated>
		<difficult>0</difficult>
		<bndbox>
			<xmin>887</xmin>
			<ymin>704</ymin>
			<xmax>932</xmax>
			<ymax>712</ymax>
		</bndbox>
	</object>
</annotation>
