<annotation verified="yes">
	<folder>result</folder>
	<filename>1-90-002.jpg</filename>
	<path>D:\Project\YoutubeData\result\1-90-002.jpg</path>
	<source>
		<database>Unknown</database>
	</source>
	<size>
		<width>1920</width>
		<height>1080</height>
		<depth>3</depth>
	</size>
	<segmented>0</segmented>
	<object>
		<name>runway</name>
		<pose>Unspecified</pose>
		<truncated>0</truncated>
		<difficult>0</difficult>
		<bndbox>
			<xmin>948</xmin>
			<ymin>507</ymin>
			<xmax>996</xmax>
			<ymax>551</ymax>
		</bndbox>
	</object>
</annotation>
